aleatoire/__init__.py
aleatoire/form.py
aleatoire/io.py
aleatoire/moment.py
aleatoire/numeric.py
aleatoire/sensitivity.py
aleatoire/systems.py
aleatoire/transform.py
aleatoire/util.py
aleatoire-0.0.2.dist-info/AUTHORS.md
aleatoire-0.0.2.dist-info/LICENSE
aleatoire-0.0.2.dist-info/METADATA
aleatoire-0.0.2.dist-info/WHEEL
aleatoire-0.0.2.dist-info/top_level.txt
aleatoire-0.0.2.dist-info/RECORD
