Metadata-Version: 2.1
Name: aleatoire
Version: 0.0.2
Summary: System reliability analysis.
Home-page: https://github.com/claudioperez/aleatoire
Author: Claudio Perez
Author-email: claudio_perez@berkeley.edu
License: Apache-2.0
Project-URL: Changelog, https://github.com/claudioperez/aleatoire/blob/master/CHANGELOG.md
Project-URL: Issue Tracker, https://github.com/claudioperez/aleatoire/issues
Keywords: reliability,form,system-reliability,nataf,copula
Platform: UNKNOWN
Classifier: Development Status :: 2 - Pre-Alpha
Classifier: Intended Audience :: Education
Classifier: License :: OSI Approved :: Apache Software License
Classifier: Operating System :: Unix
Classifier: Operating System :: POSIX
Classifier: Operating System :: Microsoft :: Windows
Classifier: Programming Language :: Python
Classifier: Programming Language :: Python :: 3
Classifier: Programming Language :: Python :: 3.7
Classifier: Programming Language :: Python :: 3.8
Classifier: Programming Language :: Python :: Implementation :: CPython
Classifier: Topic :: Scientific/Engineering
Classifier: Topic :: Education
Requires-Python: >=3.6
